filegen/__init__.py
filegen/asking.py
filegen/codegen.py
filegen/gitignore.txt
filegen/package.py
filegen/__pycache__/__init__.cpython-34.pyc
filegen/__pycache__/asking.cpython-34.pyc
filegen/tests/__init__.py
filegen/tests/__pycache__/__init__.cpython-34.pyc
filegen/tests/__pycache__/test_scan.cpython-34.pyc
filegen-0.2.1.dist-info/DESCRIPTION.rst
filegen-0.2.1.dist-info/entry_points.txt
filegen-0.2.1.dist-info/METADATA
filegen-0.2.1.dist-info/metadata.json
filegen-0.2.1.dist-info/RECORD
filegen-0.2.1.dist-info/top_level.txt
filegen-0.2.1.dist-info/WHEEL
