Metadata-Version: 2.0
Name: filegen
Version: 0.2.1
Summary: file structure generator with onefile script
Home-page: https://github.com/podhmo/filegen
Author: podhmo
Author-email: UNKNOWN
License: mit
Keywords: filegen,file generation,scaffold
Platform: UNKNOWN
Classifier: Programming Language :: Python
Classifier: Programming Language :: Python :: Implementation :: CPython
Requires-Dist: prestring
Provides-Extra: codegen
Requires-Dist: prestring; extra == 'codegen'
Provides-Extra: docs
Provides-Extra: testing
